pycurvature
