Metadata-Version: 1.1
Name: pycurvature
Version: 0.0.2
Summary: Curvature Classification
Home-page: https://github.com/ty-edelweiss/pycurvature
Author: Yusaku Takano
Author-email: takano-yuusaku@ed.tmu.ac.jp
License: MIT License
Platform: UNKNOWN
Classifier: Programming Language :: Python :: 3.6
Classifier: License :: OSI Approved :: MIT License
